kv_deta.py
kv_deta-0.2.2.post1.dist-info/LICENSE
kv_deta-0.2.2.post1.dist-info/METADATA
kv_deta-0.2.2.post1.dist-info/WHEEL
kv_deta-0.2.2.post1.dist-info/top_level.txt
kv_deta-0.2.2.post1.dist-info/RECORD
