Metadata-Version: 2.1
Name: kv-deta
Version: 0.2.2.post1
Summary: Key-Value Model for Detabase
Home-page: https://github.com/ablaternae/kv-deta
Author: d;)
License: GLWTPL
Keywords: deta,detabase,kv,key value
Classifier: Development Status :: 3 - Alpha
Classifier: Intended Audience :: Developers
Classifier: License :: OSI Approved :: GNU Affero General Public License v3
Classifier: Operating System :: OS Independent
Classifier: Programming Language :: Python :: 3
Classifier: Programming Language :: Python :: 3.7
Classifier: Programming Language :: Python :: 3.8
Classifier: Programming Language :: Python :: 3.9
Classifier: Topic :: Software Development :: Libraries :: Python Modules
Requires-Python: >=3.7
License-File: LICENSE
Requires-Dist: deta
Requires-Dist: more-itertools
